django_sales_ve-0.2.1.dist-info/licenses/LICENSE
sales/__init__.py
sales/apps.py
sales/conf.py
sales/enums.py
sales/api/serializers.py
sales/api/urls.py
sales/api/views.py
sales/mgmt/commands/sales_bootstrap_demo.py
sales/migrations/0001_initial.py
sales/models/config.py
sales/models/doc_creditnote.py
sales/models/doc_invoice.py
sales/models/doc_receipt.py
sales/models/item.py
sales/models/party.py
sales/models/tax.py
sales/posting/adapters.py
sales/posting/reversal.py
sales/posting/signals.py
sales/tests/conftest.py
sales/tests/test_creditnote_posting.py
sales/tests/test_invoice_posting.py
sales/tests/test_refund_posting.py
sales/utils/money.py
sales/utils/tax.py
django_sales_ve-0.2.1.dist-info/METADATA
django_sales_ve-0.2.1.dist-info/WHEEL
django_sales_ve-0.2.1.dist-info/top_level.txt
django_sales_ve-0.2.1.dist-info/RECORD
