Metadata-Version: 2.4
Name: django-sales-ve
Version: 0.2.1
Summary: Sales (products & services) with invoices, credit notes, receipts, refunds, GST split, and django-finacc integration.
Requires-Python: >=3.11
License-File: LICENSE
Requires-Dist: Django>=5.0
Requires-Dist: djangorestframework>=3.15
Requires-Dist: django-finacc>=0.1.0
Dynamic: license-file
